csvkit/__init__.py
csvkit/_filter.py
csvkit/sync/__init__.py
csvkit/sync/_filelock.py
csv.py-0.5.2.dist-info/LICENSE
csv.py-0.5.2.dist-info/METADATA
csv.py-0.5.2.dist-info/WHEEL
csv.py-0.5.2.dist-info/top_level.txt
csv.py-0.5.2.dist-info/RECORD
