Metadata-Version: 2.1
Name: csv.py
Version: 0.5.2
Summary: A package of tools for csv files
Home-page: https://github.com/leoxiang66/csv-toolkit
Author: Tao Xiang
Author-email: tao.xiang@tum.de
License: UNKNOWN
Platform: UNKNOWN
Classifier: Programming Language :: Python :: 3.8
Classifier: License :: OSI Approved :: MIT License
License-File: LICENSE
Requires-Dist: pandas
Requires-Dist: filelock (==3.9.0)
